tfloop/__init__.py
tfloop/tfloop.py
tfloop-0.4.dist-info/LICENCE.txt
tfloop-0.4.dist-info/METADATA
tfloop-0.4.dist-info/WHEEL
tfloop-0.4.dist-info/top_level.txt
tfloop-0.4.dist-info/RECORD
