Metadata-Version: 2.1
Name: tfloop
Version: 0.4
Summary: tensorflow utils
Home-page: UNKNOWN
Author: lmaxwell
Author-email: UNKNOWN
License: UNKNOWN
Platform: UNKNOWN
